LICENSE.md
MANIFEST.in
Makefile
README.md
requirements.txt
setup.py
images/ONT_logo_590x106.png
pomoxis/__init__.py
pomoxis/assess_homopolymers.py
pomoxis/bio.py
pomoxis/catalogue_errors.py
pomoxis/common_errors_from_bam.py
pomoxis/coverage_from_bam.py
pomoxis/filter_bam.py
pomoxis/find_indels.py
pomoxis/qscores_from_summary.py
pomoxis/ref_seqs_from_bam.py
pomoxis/stats_from_bam.py
pomoxis/subsample_bam.py
pomoxis/summary_from_stats.py
pomoxis/trim_alignments.py
pomoxis/util.py
pomoxis.egg-info/PKG-INFO
pomoxis.egg-info/SOURCES.txt
pomoxis.egg-info/dependency_links.txt
pomoxis.egg-info/entry_points.txt
pomoxis.egg-info/not-zip-safe
pomoxis.egg-info/requires.txt
pomoxis.egg-info/top_level.txt
scripts/assess_assembly
scripts/intersect_assembly_errors
scripts/mini_align
scripts/mini_assemble