Metadata-Version: 2.1
Name: pomoxis
Version: 0.3.16
Summary: Assembly, consensensus, and analysis tools by ONT research.
Author: cwright
Author-email: cwright@nanoporetech.com
Requires-Python: >=3.6
License-File: LICENSE.md
Requires-Dist: biopython<1.77,>=1.63
Requires-Dist: intervaltree>=3
Requires-Dist: matplotlib
Requires-Dist: ncls
Requires-Dist: numpy<2.0
Requires-Dist: pandas
Requires-Dist: pysam>=0.15.4
